[
 {
  "User": "Trịnh Tân",
  "Content": "Không còn mít với gà ăn nữa rồi",
  "Phone": 902196877,
  "LinkImageUse": "https://scontent.fhan17-1.fna.fbcdn.net/v/t39.30808-6/335049138_719038356676796_4922898347675381291_n.jpg?_nc_cat=108&ccb=1-7&_nc_sid=be3454&_nc_ohc=ArgpJpRcVl4AX-YLXA2&_nc_ht=scontent.fhan17-1.fna&oh=00_AfAC0WFwMusBOlLmmkRN8Wy1oIDcmuzspY58fYOpDCVQyQ&oe=64DFBE9E",
  "LinkImageStatus": "https://scontent.fhan17-1.fna.fbcdn.net/v/t1.6435-9/67717312_2285323088201118_3923557009781161984_n.jpg?_nc_cat=102&ccb=1-7&_nc_sid=dd63ad&_nc_ohc=tOpRFI7gc_sAX8jum0L&_nc_ht=scontent.fhan17-1.fna&oh=00_AfDvii9blI5i1k_35WwDfxyZpJV93MIMoafOxqjsK22UIw&oe=65029897"

 },
  {
  "User": "Trịnh Tân",
  "Content": "Tạm biệt Sài Gòn nơi gắn bó một thời tuổi thanh xuân, cảm ơn các bạn đã cho tôi sống lại những giây phút thời sinh viên. Cảm ơn em đã là hậu phương cho a để a có những phút giây vui vẻ như thế này !",
  "time": "2h trước",
  "LinkImageUse": "https://scontent.fhan17-1.fna.fbcdn.net/v/t39.30808-6/335049138_719038356676796_4922898347675381291_n.jpg?_nc_cat=108&ccb=1-7&_nc_sid=be3454&_nc_ohc=ArgpJpRcVl4AX-YLXA2&_nc_ht=scontent.fhan17-1.fna&oh=00_AfAC0WFwMusBOlLmmkRN8Wy1oIDcmuzspY58fYOpDCVQyQ&oe=64DFBE9E",
  "LinkImageStatus": "https://scontent.fhan17-1.fna.fbcdn.net/v/t1.6435-9/67318956_2285323114867782_7020102729389309952_n.jpg?_nc_cat=102&ccb=1-7&_nc_sid=dd63ad&_nc_ohc=9wKT9iLQqykAX_HbtG_&_nc_ht=scontent.fhan17-1.fna&oh=00_AfCIsIQXzYBCVWNIFOO7yBkILL0WejyQo3LyDDtEG0LsEw&oe=65028CB6"
 },
  {
  "User": "Trịnh Tân",
  "Content": "Caffe thôi",
  "time": "2h trước",
  "LinkImageUse": "https://scontent.fhan17-1.fna.fbcdn.net/v/t39.30808-6/335049138_719038356676796_4922898347675381291_n.jpg?_nc_cat=108&ccb=1-7&_nc_sid=be3454&_nc_ohc=ArgpJpRcVl4AX-YLXA2&_nc_ht=scontent.fhan17-1.fna&oh=00_AfAC0WFwMusBOlLmmkRN8Wy1oIDcmuzspY58fYOpDCVQyQ&oe=64DFBE9E",
  "LinkImageStatus": "https://scontent.fhan17-1.fna.fbcdn.net/v/t1.6435-9/67418385_2285323161534444_1387672846364311552_n.jpg?_nc_cat=104&ccb=1-7&_nc_sid=dd63ad&_nc_ohc=pZGbb0EQHVUAX866lTJ&_nc_ht=scontent.fhan17-1.fna&oh=00_AfDgQLHphC1sOJDuuwu0yrmn6w8mkcT5XeiNxU8mIDSbvA&oe=6502BB52"
 },
  {
  "User": "Trịnh Tân",
  "Content": "Khai giảng đầu tiên của chị cả Su",
  "time": "2h trước",
  "LinkImageUse":"https://scontent.fhan17-1.fna.fbcdn.net/v/t39.30808-6/335049138_719038356676796_4922898347675381291_n.jpg?_nc_cat=108&ccb=1-7&_nc_sid=be3454&_nc_ohc=ArgpJpRcVl4AX-YLXA2&_nc_ht=scontent.fhan17-1.fna&oh=00_AfAC0WFwMusBOlLmmkRN8Wy1oIDcmuzspY58fYOpDCVQyQ&oe=64DFBE9E",
  "LinkImageStatus": "https://scontent.fhan17-1.fna.fbcdn.net/v/t1.6435-9/67398347_2285323188201108_4080217874638045184_n.jpg?_nc_cat=104&ccb=1-7&_nc_sid=dd63ad&_nc_ohc=PKqBzNgs49oAX-3S458&_nc_ht=scontent.fhan17-1.fna&oh=00_AfB4SSeoaU2ZC4H4bPgOXZCNyaKjr0nG4WFHNX1dtcmUzA&oe=65028629"
 }
  
]
